gloom/__init__.py
gloom/__main__.py
gloom/cli.py
gloom/core/__init__.py
gloom/core/adc.py
gloom/core/config.py
gloom/core/gcloud.py
gloom/core/symlink.py
gloom/integrations/__init__.py
gloom/integrations/direnv.py
gloom/integrations/prompt.py
gloom/security/__init__.py
gloom/security/audit.py
gloom/security/permissions.py
gloom/security/validator.py
gloom/utils/__init__.py
gloom/utils/logger.py
gloom/utils/shell.py
gloom_cli-0.2.0.dist-info/METADATA
gloom_cli-0.2.0.dist-info/WHEEL
gloom_cli-0.2.0.dist-info/entry_points.txt
gloom_cli-0.2.0.dist-info/licenses/LICENSE
gloom_cli-0.2.0.dist-info/RECORD
