Metadata-Version: 2.4
Name: gloom-cli
Version: 0.2.0
Summary: A high-performance CLI for Google Cloud Context & ADC Switching
Project-URL: Homepage, https://github.com/hilmanmustofaa/gloom
Project-URL: Documentation, https://github.com/hilmanmustofaa/gloom#readme
Project-URL: Repository, https://github.com/hilmanmustofaa/gloom
Project-URL: Issues, https://github.com/hilmanmustofaa/gloom/issues
Author-email: Hilman Mustofa <hilmanmustofa@gmail.com>
License-Expression: MIT
License-File: LICENSE
Keywords: adc,cli,devops,gcloud,google-cloud
Classifier: Development Status :: 3 - Alpha
Classifier: Environment :: Console
Classifier: Intended Audience :: Developers
Classifier: License :: OSI Approved :: MIT License
Classifier: Operating System :: OS Independent
Classifier: Programming Language :: Python :: 3
Classifier: Programming Language :: Python :: 3.10
Classifier: Programming Language :: Python :: 3.11
Classifier: Programming Language :: Python :: 3.12
Classifier: Topic :: Software Development :: Libraries :: Python Modules
Classifier: Topic :: System :: Systems Administration
Requires-Python: >=3.10
Requires-Dist: pydantic-settings>=2.0.0
Requires-Dist: pydantic>=2.0.0
Requires-Dist: rich>=13.0.0
Requires-Dist: typer>=0.9.0
Provides-Extra: dev
Requires-Dist: bandit[toml]>=1.7.0; extra == 'dev'
Requires-Dist: mypy>=1.0.0; extra == 'dev'
Requires-Dist: pre-commit>=3.0.0; extra == 'dev'
Requires-Dist: pytest-cov>=4.0.0; extra == 'dev'
Requires-Dist: pytest-mock>=3.0.0; extra == 'dev'
Requires-Dist: pytest>=7.0.0; extra == 'dev'
Requires-Dist: ruff>=0.1.0; extra == 'dev'
